pm/__init__.py
pm/main.py
pm/schema.py
pm/settings.py
pm/utils.py
pm/commands/__init__.py
pm/commands/create.py
pm/commands/kill.py
pm/commands/ls.py
pmflow-1.2.16.dist-info/LICENSE
pmflow-1.2.16.dist-info/METADATA
pmflow-1.2.16.dist-info/WHEEL
pmflow-1.2.16.dist-info/entry_points.txt
pmflow-1.2.16.dist-info/top_level.txt
pmflow-1.2.16.dist-info/RECORD
