Metadata-Version: 2.1
Name: pmflow
Version: 1.2.16
Summary: Manages processes
Author-email: "Md. Mahmudul Hasan Riyad" <mhriyad98@gmail.com>
License: MIT License
Project-URL: Homepage, https://github.com/mhriyad99/process_manager
Keywords: process manager,process,pm
Classifier: License :: OSI Approved :: MIT License
Classifier: Programming Language :: Python
Classifier: Programming Language :: Python :: 3
Requires-Python: >=3.10
License-File: LICENSE
Requires-Dist: typer==0.12.5
Requires-Dist: psutil==6.0.0
Provides-Extra: dev
